pymaestro/__init__.py
pymaestro/cli.py
pymaestro/job_registry.py
pymaestro/jobs.py
pymaestro/maestro.py
pymaestro/utils/__init__.py
pymaestro/utils/deserialize.py
pymaestro/utils/dispatcher.py
pymaestro/utils/serialize.py
pymaestro/utils/wrappers.py
python_maestro-0.2.0.dist-info/METADATA
python_maestro-0.2.0.dist-info/WHEEL
python_maestro-0.2.0.dist-info/entry_points.txt
python_maestro-0.2.0.dist-info/licenses/LICENSE
python_maestro-0.2.0.dist-info/RECORD
