Metadata-Version: 2.4
Name: python-maestro
Version: 0.2.0
Summary: A lightweight orchestrator for managing Python tasks
License: MIT
License-File: LICENSE
Keywords: orchestration,task-scheduler,python,CLI
Author: Ioannis Mougios
Author-email: i.mougios.tech@gmail.com
Requires-Python: >=3.12
Classifier: License :: OSI Approved :: MIT License
Classifier: Programming Language :: Python :: 3
Classifier: Programming Language :: Python :: 3.12
Classifier: Programming Language :: Python :: 3.13
Classifier: Programming Language :: Python :: 3.14
Provides-Extra: cli
Requires-Dist: click (>=8.3.0,<9.0.0) ; extra == "cli"
Requires-Dist: wrapt (>=2.0.1,<3.0.0)
Project-URL: Homepage, https://github.com/I-Mougios/pymaestro
Project-URL: Repository, https://github.com/I-Mougios/pymaestro
